statuscast/__init__.py
statuscast/caster.py
statuscast-0.0.1.dist-info/LICENSE
statuscast-0.0.1.dist-info/METADATA
statuscast-0.0.1.dist-info/WHEEL
statuscast-0.0.1.dist-info/top_level.txt
statuscast-0.0.1.dist-info/RECORD
